authValid/__init__.py
authValid/token_manager.py
token_forge/__init__.py
token_forge/token_manager.py
AuthValid-0.1.dist-info/LICENSE
AuthValid-0.1.dist-info/METADATA
AuthValid-0.1.dist-info/WHEEL
AuthValid-0.1.dist-info/top_level.txt
AuthValid-0.1.dist-info/RECORD
