Metadata-Version: 2.1
Name: AuthValid
Version: 0.1
Summary: A package for JWT token management and authentication
Home-page: https://github.com/ridzwansyahirwan/AuthValid.git
Author: Mohammad Ridzwan Syah bin Irwan
Author-email: ridzwansyahirwan@gmail.com
License-File: LICENSE
Requires-Dist: Flask
Requires-Dist: python-dotenv
Requires-Dist: PyJWT
